waifu2x_vulkan/__init__.py
waifu2x_vulkan/hook-waifu2x_vulkan.py
waifu2x_vulkan/waifu2x.py
waifu2x_vulkan/waifu2x_vulkan.pyd
waifu2x_vulkan/waifu2x_vulkan.pyi
waifu2x_vulkan/__pycache__/__init__.cpython-37.pyc
waifu2x_vulkan/models/models-cunet/noise0_model.bin
waifu2x_vulkan/models/models-cunet/noise0_model.param
waifu2x_vulkan/models/models-cunet/noise0_scale2.0x_model.bin
waifu2x_vulkan/models/models-cunet/noise0_scale2.0x_model.param
waifu2x_vulkan/models/models-cunet/noise1_model.bin
waifu2x_vulkan/models/models-cunet/noise1_model.param
waifu2x_vulkan/models/models-cunet/noise1_scale2.0x_model.bin
waifu2x_vulkan/models/models-cunet/noise1_scale2.0x_model.param
waifu2x_vulkan/models/models-cunet/noise2_model.bin
waifu2x_vulkan/models/models-cunet/noise2_model.param
waifu2x_vulkan/models/models-cunet/noise2_scale2.0x_model.bin
waifu2x_vulkan/models/models-cunet/noise2_scale2.0x_model.param
waifu2x_vulkan/models/models-cunet/noise3_model.bin
waifu2x_vulkan/models/models-cunet/noise3_model.param
waifu2x_vulkan/models/models-cunet/noise3_scale2.0x_model.bin
waifu2x_vulkan/models/models-cunet/noise3_scale2.0x_model.param
waifu2x_vulkan/models/models-cunet/scale2.0x_model.bin
waifu2x_vulkan/models/models-cunet/scale2.0x_model.param
waifu2x_vulkan/models/models-upconv_7_anime_style_art_rgb/noise0_scale2.0x_model.bin
waifu2x_vulkan/models/models-upconv_7_anime_style_art_rgb/noise0_scale2.0x_model.param
waifu2x_vulkan/models/models-upconv_7_anime_style_art_rgb/noise1_scale2.0x_model.bin
waifu2x_vulkan/models/models-upconv_7_anime_style_art_rgb/noise1_scale2.0x_model.param
waifu2x_vulkan/models/models-upconv_7_anime_style_art_rgb/noise2_scale2.0x_model.bin
waifu2x_vulkan/models/models-upconv_7_anime_style_art_rgb/noise2_scale2.0x_model.param
waifu2x_vulkan/models/models-upconv_7_anime_style_art_rgb/noise3_scale2.0x_model.bin
waifu2x_vulkan/models/models-upconv_7_anime_style_art_rgb/noise3_scale2.0x_model.param
waifu2x_vulkan-1.1.6.dist-info/LICENSE
waifu2x_vulkan-1.1.6.dist-info/METADATA
waifu2x_vulkan-1.1.6.dist-info/WHEEL
waifu2x_vulkan-1.1.6.dist-info/entry_points.txt
waifu2x_vulkan-1.1.6.dist-info/top_level.txt
waifu2x_vulkan-1.1.6.dist-info/RECORD
